spycalc/__init__.py
spycalc/__main__.py
spycalc/docs.html
spycalc/loaded.py
spycalc/loadedfunctions.ui
spycalc/loading.gif
spycalc/local.py
spycalc/main.ui
spycalc/update.py
spycalc/update.ui
spycalc/extensions/__init__.py
spycalc/extensions/examples.py
spycalc/extensions/geo1.py
spycalc/extensions/physics.py
spycalc-0.1.3.dist-info/LICENSE
spycalc-0.1.3.dist-info/METADATA
spycalc-0.1.3.dist-info/WHEEL
spycalc-0.1.3.dist-info/top_level.txt
spycalc-0.1.3.dist-info/RECORD
