Metadata-Version: 2.1
Name: spycalc
Version: 0.1.3
Summary: extensibly scriptable graphical calculator
Home-page: https://github.com/Krayfighter/spycalc
Author: Aiden Kring
Author-email: ajkraayfighter@protonmail.com
License: UNKNOWN
Project-URL: Bug Tracker, https://github.com/Krayfighter/spycalc/issues
Platform: UNKNOWN
Classifier: Programming Language :: Python :: 3
Classifier: Operating System :: OS Independent
License-File: LICENSE
Requires-Dist: pyqt5
Requires-Dist: sympy
Requires-Dist: pyshortcuts
